JingtongPandasChuyiFix1/README.md
JingtongPandasChuyiFix1/__init__.py
JingtongPandasChuyiFix1/__main__.py
JingtongPandasChuyiFix1/file.epub
JingtongPandasChuyiFix1/index.html
JingtongPandasChuyiFix1/css/__init__.py
JingtongPandasChuyiFix1/css/annotations.css
JingtongPandasChuyiFix1/css/main.css
JingtongPandasChuyiFix1/css/normalize.css
JingtongPandasChuyiFix1/css/popup.css
JingtongPandasChuyiFix1/font/__init__.py
JingtongPandasChuyiFix1/font/fontello.eot
JingtongPandasChuyiFix1/font/fontello.svg
JingtongPandasChuyiFix1/font/fontello.ttf
JingtongPandasChuyiFix1/font/fontello.woff
JingtongPandasChuyiFix1/img/__init__.py
JingtongPandasChuyiFix1/img/annotator-glyph-sprite.png
JingtongPandasChuyiFix1/img/annotator-icon-sprite.png
JingtongPandasChuyiFix1/img/apple-touch-icon.png
JingtongPandasChuyiFix1/img/cancelfullscreen.png
JingtongPandasChuyiFix1/img/close.png
JingtongPandasChuyiFix1/img/fullscreen.png
JingtongPandasChuyiFix1/img/loader.gif
JingtongPandasChuyiFix1/img/menu-icon.png
JingtongPandasChuyiFix1/img/save.png
JingtongPandasChuyiFix1/img/saved.png
JingtongPandasChuyiFix1/img/settings-s.png
JingtongPandasChuyiFix1/img/settings.png
JingtongPandasChuyiFix1/img/star.png
JingtongPandasChuyiFix1/js/__init__.py
JingtongPandasChuyiFix1/js/epub.js
JingtongPandasChuyiFix1/js/epub.min.js
JingtongPandasChuyiFix1/js/epub.min.map
JingtongPandasChuyiFix1/js/hooks.min.js
JingtongPandasChuyiFix1/js/hooks.min.map
JingtongPandasChuyiFix1/js/reader.js
JingtongPandasChuyiFix1/js/reader.js.map
JingtongPandasChuyiFix1/js/reader.min.js
JingtongPandasChuyiFix1/js/reader.min.map
JingtongPandasChuyiFix1/js/hooks/__init__.py
JingtongPandasChuyiFix1/js/hooks/extensions/__init__.py
JingtongPandasChuyiFix1/js/hooks/extensions/highlight.js
JingtongPandasChuyiFix1/js/libs/__init__.py
JingtongPandasChuyiFix1/js/libs/jquery.min.js
JingtongPandasChuyiFix1/js/libs/localforage.min.js
JingtongPandasChuyiFix1/js/libs/screenfull.js
JingtongPandasChuyiFix1/js/libs/screenfull.min.js
jingtong_pandas_chuyi_fix1-2025.3.24.1.dist-info/METADATA
jingtong_pandas_chuyi_fix1-2025.3.24.1.dist-info/WHEEL
jingtong_pandas_chuyi_fix1-2025.3.24.1.dist-info/entry_points.txt
jingtong_pandas_chuyi_fix1-2025.3.24.1.dist-info/top_level.txt
jingtong_pandas_chuyi_fix1-2025.3.24.1.dist-info/RECORD
